clack/__init__.py
clack/_config.py
clack/_config_file.py
clack/_dynvars.py
clack/_helpers.py
clack/_main.py
clack/_parser.py
clack/py.typed
clack/pytest_plugin.py
clack/types.py
clack/xdg.py
bolton_clack-0.3.12.dist-info/METADATA
bolton_clack-0.3.12.dist-info/WHEEL
bolton_clack-0.3.12.dist-info/top_level.txt
bolton_clack-0.3.12.dist-info/RECORD
