Metadata-Version: 2.1
Name: bolton-clack
Version: 0.3.12
Summary: command-line application configuration kit (CLACK)... A wrapper around the `argparse` library that aims to handle _all_ application configuration.
Home-page: https://github.com/python-boltons/clack
Author: Bryan M Bugyi
Author-email: bryanbugyi34@gmail.com
License: MIT license
Classifier: Development Status :: 3 - Alpha
Classifier: Intended Audience :: Developers
Classifier: License :: OSI Approved :: MIT License
Classifier: Natural Language :: English
Classifier: Programming Language :: Python :: 3
Classifier: Programming Language :: Python :: 3.9
Classifier: Programming Language :: Python :: 3.10
Classifier: Programming Language :: Python :: 3.11
Classifier: Programming Language :: Python :: 3.12
Requires-Python: >=3.9
Requires-Dist: bolton-eris ~=0.2.2
Requires-Dist: bolton-logrus ~=0.1.0
Requires-Dist: bolton-typist ~=0.2.0
Requires-Dist: pydantic ~=2.6
Requires-Dist: pydantic-settings ~=2.2
Requires-Dist: pyyaml ~=6.0
